MANIFEST.in
README.md
pyproject.toml
setup.py
pystru/cli.py
pystru/setting.py
pystru/temp.py
pystru.egg-info/PKG-INFO
pystru.egg-info/SOURCES.txt
pystru.egg-info/dependency_links.txt
pystru.egg-info/entry_points.txt
pystru.egg-info/requires.txt
pystru.egg-info/top_level.txt
pystru/templates/README.md
pystru/templates/mkdocs.yml
pystru/templates/structure.toml
pystru/templates/demo/demo.py
pystru/templates/demo/md_demo.md
pystru/templates/demo/py_demo.md
pystru/templates/files/.gitignore
pystru/templates/files/Makefile
pystru/templates/files/requirements.txt